{"features":[{"properties":{"source":"DEEP-unlock","reference":"HL/PO/JO/10/1/77/3","name":"Appleford"},"geometry":{"type":"Point","coordinates":[-1.24129,51.6374]},"type":"Feature"},{"geometry":{"type":"Point","coordinates":[-1.24077,51.6392]},"properties":{"source":"DEEP-geonames","reference":"HL/PO/JO/10/1/77/3","name":"Appleford"},"type":"Feature"},{"type":"Feature","geometry":{"coordinates":[-1.24276,51.6379],"type":"Point"},"properties":{"name":"Appleford","reference":"HL/PO/JO/10/1/77/3","source":"DEEP-kepn"}},{"type":"Feature","properties":{"name":"Appleton","source":"DEEP-geonames","reference":"HL/PO/JO/10/1/77/4"},"geometry":{"coordinates":[-2.57183,53.3524],"type":"Point"}},{"geometry":{"type":"Point","coordinates":[-2.55579,53.3423]},"properties":{"name":"Appleton","source":"DEEP-epns","reference":"HL/PO/JO/10/1/77/4"},"type":"Feature"},{"type":"Feature","properties":{"name":"Appleton","reference":"HL/PO/JO/10/1/77/4","source":"DEEP-unlock"},"geometry":{"coordinates":[-2.54834,53.3469],"type":"Point"}},{"type":"Feature","geometry":{"coordinates":[-1.18607,51.4931],"type":"Point"},"properties":{"name":"Ashampstead","source":"DEEP-unlock","reference":"HL/PO/JO/10/1/77/5"}},{"type":"Feature","geometry":{"coordinates":[-1.1877,51.4846],"type":"Point"},"properties":{"name":"Ashampstead","reference":"HL/PO/JO/10/1/77/5","source":"DEEP-kepn"}},{"properties":{"reference":"HL/PO/JO/10/1/77/5","source":"DEEP-geonames","name":"Ashampstead"},"geometry":{"coordinates":[-1.18391,51.4822],"type":"Point"},"type":"Feature"},{"geometry":{"coordinates":[-1.19921,51.5652],"type":"Point"},"properties":{"reference":"HL/PO/JO/10/1/77/6","source":"DEEP-unlock","name":"Aston Tirrold"},"type":"Feature"},{"type":"Feature","geometry":{"type":"Point","coordinates":[-1.20052,51.5746]},"properties":{"name":"Aston Tirrold","reference":"HL/PO/JO/10/1/77/6","source":"DEEP-kepn"}},{"geometry":{"type":"Point","coordinates":[-1.19581,51.5612]},"properties":{"reference":"HL/PO/JO/10/1/77/6","source":"DEEP-geonames","name":"Aston Tirrold"},"type":"Feature"},{"type":"Feature","geometry":{"coordinates":[-1.14302,51.4838],"type":"Point"},"properties":{"name":"Basildon","reference":"HL/PO/JO/10/1/77/8","source":"DEEP-unlock"}},{"type":"Feature","geometry":{"coordinates":[-1.1445,51.4843],"type":"Point"},"properties":{"reference":"HL/PO/JO/10/1/77/8","source":"DEEP-kepn","name":"Basildon"}},{"type":"Feature","geometry":{"type":"Point","coordinates":[-1.11667,51.5]},"properties":{"name":"Basildon","reference":"HL/PO/JO/10/1/77/8","source":"DEEP-geonames"}},{"properties":{"name":"Drayton","source":"DEEP-geonames","reference":"HL/PO/JO/10/1/77/11"},"geometry":{"coordinates":[-0.821,52.533],"type":"Point"},"type":"Feature"},{"geometry":{"type":"Point","coordinates":[-0.827851,52.5332]},"properties":{"reference":"HL/PO/JO/10/1/77/11","source":"DEEP-unlock","name":"Drayton"},"type":"Feature"},{"type":"Feature","geometry":{"coordinates":[-0.829405,52.5336],"type":"Point"},"properties":{"source":"DEEP-kepn","reference":"HL/PO/JO/10/1/77/11","name":"Drayton"}},{"type":"Feature","properties":{"reference":"HL/PO/JO/10/1/77/13","source":"DEEP-geonames","name":"Frilford"},"geometry":{"coordinates":[-1.37444,51.6755],"type":"Point"}},{"type":"Feature","geometry":{"type":"Point","coordinates":[-1.35785,51.6745]},"properties":{"reference":"HL/PO/JO/10/1/77/13","source":"DEEP-kepn","name":"Frilford"}},{"properties":{"name":"Frilford","source":"DEEP-unlock","reference":"HL/PO/JO/10/1/77/13"},"geometry":{"type":"Point","coordinates":[-1.37085,51.6741]},"type":"Feature"},{"geometry":{"type":"Point","coordinates":[-1.79287,51.4153]},"properties":{"reference":"HL/PO/JO/10/1/77/14","source":"DEEP-kepn","name":"Fyfield"},"type":"Feature"},{"type":"Feature","properties":{"name":"Fyfield","reference":"HL/PO/JO/10/1/77/14","source":"DEEP-geonames"},"geometry":{"type":"Point","coordinates":[-1.78333,51.4167]}},{"geometry":{"type":"Point","coordinates":[-1.79147,51.4148]},"properties":{"name":"Fyfield","source":"DEEP-unlock","reference":"HL/PO/JO/10/1/77/14"},"type":"Feature"},{"type":"Feature","geometry":{"coordinates":[-1.38543,51.6652],"type":"Point"},"properties":{"name":"Garford","source":"DEEP-unlock","reference":"HL/PO/JO/10/1/77/15"}},{"type":"Feature","geometry":{"coordinates":[-1.38406,51.6628],"type":"Point"},"properties":{"source":"DEEP-geonames","reference":"HL/PO/JO/10/1/77/15","name":"Garford"}},{"type":"Feature","properties":{"name":"Garford","source":"DEEP-kepn","reference":"HL/PO/JO/10/1/77/15"},"geometry":{"coordinates":[-1.38689,51.6657],"type":"Point"}},{"geometry":{"coordinates":[-0.99317,52.5975],"type":"Point"},"properties":{"source":"DEEP-geonames","reference":"HL/PO/JO/10/1/77/17","name":"Hagbourne, East and West"},"type":"Feature"},{"geometry":{"coordinates":[-0.988559,52.5976],"type":"Point"},"properties":{"name":"Hagbourne, East and West","reference":"HL/PO/JO/10/1/77/17","source":"DEEP-unlock"},"type":"Feature"},{"properties":{"source":"DEEP-kepn","reference":"HL/PO/JO/10/1/77/17","name":"Hagbourne, East and West"},"geometry":{"coordinates":[-0.990097,52.598],"type":"Point"},"type":"Feature"},{"type":"Feature","geometry":{"type":"Point","coordinates":[-1.28521,51.6017]},"properties":{"reference":"HL/PO/JO/10/1/77/18","source":"DEEP-unlock","name":"Harwell"}},{"type":"Feature","geometry":{"type":"Point","coordinates":[-1.29175,51.5995]},"properties":{"name":"Harwell","source":"DEEP-geonames","reference":"HL/PO/JO/10/1/77/18"}},{"properties":{"reference":"HL/PO/JO/10/1/77/18","source":"DEEP-kepn","name":"Harwell"},"geometry":{"coordinates":[-1.28667,51.6022],"type":"Point"},"type":"Feature"}],"type":"FeatureCollection"}